{
  "deviceId": "1778265455104-073fcf82",
  "status": "queued",
  "createdAt": "2026-05-08T18:37:35.104Z",
  "hardwareIdHash": "221744a9edc045690cc6aca07c474b223a661f7a7ab887debfacf41e065d9f3c",
  "model": "GALACTIC-BEACON-v14",
  "firmwareVersion": "14.0.0-galactic",
  "location": "PROXIMA-CENTAURI-B",
  "ts": "2026-05-08T18:37:35.104Z",
  "initialTelemetry": {
    "latency": 832,
    "signalStrength": "0.9019",
    "galactic_sync": true
  },
  "source": "api",
  "updatedAt": "2026-05-08T18:37:35.105Z",
  "queuedAt": "2026-05-08T18:37:35.104Z"
}