{
  "deviceId": "1778265491399-b5ad02c6",
  "status": "queued",
  "createdAt": "2026-05-08T18:38:11.399Z",
  "hardwareIdHash": "42015ab930b08566b31a17c8c617df35e083c9e9c870dbcb76ac25f3998f6069",
  "model": "GALACTIC-BEACON-v14",
  "firmwareVersion": "14.0.0-galactic",
  "location": "PROXIMA-CENTAURI-B",
  "ts": "2026-05-08T18:38:11.399Z",
  "initialTelemetry": {
    "latency": 127,
    "signalStrength": "0.2885",
    "galactic_sync": true
  },
  "source": "api",
  "updatedAt": "2026-05-08T18:38:11.402Z",
  "queuedAt": "2026-05-08T18:38:11.401Z"
}