{
  "deviceId": "1778265585596-0005165e",
  "status": "queued",
  "createdAt": "2026-05-08T18:39:45.596Z",
  "hardwareIdHash": "f79ff5eaf17735db5482d971fea19208b7550001e9699c6f87a3b9c91e6c2452",
  "model": "GALACTIC-BEACON-v14",
  "firmwareVersion": "14.0.0-galactic",
  "location": "PROXIMA-CENTAURI-B",
  "ts": "2026-05-08T18:39:45.596Z",
  "initialTelemetry": {
    "latency": 1809,
    "signalStrength": "0.0900",
    "galactic_sync": true
  },
  "source": "api",
  "updatedAt": "2026-05-08T18:39:45.597Z",
  "queuedAt": "2026-05-08T18:39:45.597Z"
}