{
  "deviceId": "1778265599737-ede83868",
  "status": "queued",
  "createdAt": "2026-05-08T18:39:59.737Z",
  "hardwareIdHash": "bde4b786acafa22011dbe43d1c95fdd695dcfe0e58b1da8f44b866a2a201de09",
  "model": "GALACTIC-BEACON-v14",
  "firmwareVersion": "14.0.0-galactic",
  "location": "PROXIMA-CENTAURI-B",
  "ts": "2026-05-08T18:39:59.737Z",
  "initialTelemetry": {
    "latency": 2094,
    "signalStrength": "0.1996",
    "galactic_sync": true
  },
  "source": "api",
  "updatedAt": "2026-05-08T18:39:59.739Z",
  "queuedAt": "2026-05-08T18:39:59.739Z"
}