{
  "deviceId": "1778265525581-63b79eb2",
  "status": "queued",
  "createdAt": "2026-05-08T18:38:45.581Z",
  "hardwareIdHash": "13157a5866932bb33ba218c0ea55ffdd99e0004be868c9c5667c4c760463622b",
  "model": "GALACTIC-BEACON-v14",
  "firmwareVersion": "14.0.0-galactic",
  "location": "PROXIMA-CENTAURI-B",
  "ts": "2026-05-08T18:38:45.581Z",
  "initialTelemetry": {
    "latency": 676,
    "signalStrength": "0.9001",
    "galactic_sync": true
  },
  "source": "api",
  "updatedAt": "2026-05-08T18:38:45.581Z",
  "queuedAt": "2026-05-08T18:38:45.581Z"
}