{
  "deviceId": "1778265526888-2bf931e5",
  "status": "queued",
  "createdAt": "2026-05-08T18:38:46.888Z",
  "hardwareIdHash": "e4292296f759666fd6820f9804d8a2cf1ec9eb6d96a0f22d82701e2875f4992e",
  "model": "GALACTIC-BEACON-v14",
  "firmwareVersion": "14.0.0-galactic",
  "location": "PROXIMA-CENTAURI-B",
  "ts": "2026-05-08T18:38:46.888Z",
  "initialTelemetry": {
    "latency": 3798,
    "signalStrength": "0.3640",
    "galactic_sync": true
  },
  "source": "api",
  "updatedAt": "2026-05-08T18:38:46.889Z",
  "queuedAt": "2026-05-08T18:38:46.889Z"
}