{
  "deviceId": "1778265517718-1fa5e35a",
  "status": "queued",
  "createdAt": "2026-05-08T18:38:37.718Z",
  "hardwareIdHash": "56f4bd69dcfe0551f007df87d40d4fb2204d34fec1cfbbf0e65ad777fb98878c",
  "model": "GALACTIC-BEACON-v14",
  "firmwareVersion": "14.0.0-galactic",
  "location": "PROXIMA-CENTAURI-B",
  "ts": "2026-05-08T18:38:37.718Z",
  "initialTelemetry": {
    "latency": 2890,
    "signalStrength": "0.0106",
    "galactic_sync": true
  },
  "source": "api",
  "updatedAt": "2026-05-08T18:38:37.720Z",
  "queuedAt": "2026-05-08T18:38:37.720Z"
}