{
  "deviceId": "1778265595432-048a46a6",
  "status": "queued",
  "createdAt": "2026-05-08T18:39:55.432Z",
  "hardwareIdHash": "9a72fd420ad8b202983009478c702e38e9149a13bad89659d4b8eb187fa3724c",
  "model": "GALACTIC-BEACON-v14",
  "firmwareVersion": "14.0.0-galactic",
  "location": "PROXIMA-CENTAURI-B",
  "ts": "2026-05-08T18:39:55.432Z",
  "initialTelemetry": {
    "latency": 4226,
    "signalStrength": "0.5871",
    "galactic_sync": true
  },
  "source": "api",
  "updatedAt": "2026-05-08T18:39:55.433Z",
  "queuedAt": "2026-05-08T18:39:55.433Z"
}