{
  "deviceId": "1778265512705-0c208e3b",
  "status": "queued",
  "createdAt": "2026-05-08T18:38:32.705Z",
  "hardwareIdHash": "846725d3c3e7a98fb11fa8ad3902bb567ff15c5c1dfd8f8b0dec4b389adb3f2b",
  "model": "GALACTIC-BEACON-v14",
  "firmwareVersion": "14.0.0-galactic",
  "location": "PROXIMA-CENTAURI-B",
  "ts": "2026-05-08T18:38:32.705Z",
  "initialTelemetry": {
    "latency": 1135,
    "signalStrength": "0.2698",
    "galactic_sync": true
  },
  "source": "api",
  "updatedAt": "2026-05-08T18:38:32.706Z",
  "queuedAt": "2026-05-08T18:38:32.706Z"
}