{
  "deviceId": "1778265568735-00676c93",
  "status": "queued",
  "createdAt": "2026-05-08T18:39:28.735Z",
  "hardwareIdHash": "743c4e20be2bf8d442a71ad0af06e2fa6db6e0b8f293082109042a9461b35d45",
  "model": "GALACTIC-BEACON-v14",
  "firmwareVersion": "14.0.0-galactic",
  "location": "PROXIMA-CENTAURI-B",
  "ts": "2026-05-08T18:39:28.735Z",
  "initialTelemetry": {
    "latency": 373,
    "signalStrength": "0.8079",
    "galactic_sync": true
  },
  "source": "api",
  "updatedAt": "2026-05-08T18:39:28.736Z",
  "queuedAt": "2026-05-08T18:39:28.736Z"
}