{
  "deviceId": "1778265541351-173b48f2",
  "status": "queued",
  "createdAt": "2026-05-08T18:39:01.351Z",
  "hardwareIdHash": "bfdab9718d52abb1e471bd087327ad1c4f41458609ff62aab170d16bf9631d4b",
  "model": "GALACTIC-BEACON-v14",
  "firmwareVersion": "14.0.0-galactic",
  "location": "PROXIMA-CENTAURI-B",
  "ts": "2026-05-08T18:39:01.351Z",
  "initialTelemetry": {
    "latency": 2408,
    "signalStrength": "0.2744",
    "galactic_sync": true
  },
  "source": "api",
  "updatedAt": "2026-05-08T18:39:01.353Z",
  "queuedAt": "2026-05-08T18:39:01.352Z"
}