{
  "deviceId": "1778265635189-c225e208",
  "status": "queued",
  "createdAt": "2026-05-08T18:40:35.189Z",
  "hardwareIdHash": "01445344d07ccec465dccf078f737952b0d6df40f21b3bdec2ee8db95fba97f4",
  "model": "GALACTIC-BEACON-v14",
  "firmwareVersion": "14.0.0-galactic",
  "location": "PROXIMA-CENTAURI-B",
  "ts": "2026-05-08T18:40:35.189Z",
  "initialTelemetry": {
    "latency": 1395,
    "signalStrength": "0.3560",
    "galactic_sync": true
  },
  "source": "api",
  "updatedAt": "2026-05-08T18:40:35.191Z",
  "queuedAt": "2026-05-08T18:40:35.190Z"
}