{
  "deviceId": "1778265565071-1b4eb4ca",
  "status": "queued",
  "createdAt": "2026-05-08T18:39:25.071Z",
  "hardwareIdHash": "6001f697a84b6101a2782466b0ccf24706be59d27abbb4c27bb175a732fcb65a",
  "model": "GALACTIC-BEACON-v14",
  "firmwareVersion": "14.0.0-galactic",
  "location": "PROXIMA-CENTAURI-B",
  "ts": "2026-05-08T18:39:25.071Z",
  "initialTelemetry": {
    "latency": 4182,
    "signalStrength": "0.5438",
    "galactic_sync": true
  },
  "source": "api",
  "updatedAt": "2026-05-08T18:39:25.071Z",
  "queuedAt": "2026-05-08T18:39:25.071Z"
}