{
  "deviceId": "1778265600514-479510ab",
  "status": "queued",
  "createdAt": "2026-05-08T18:40:00.514Z",
  "hardwareIdHash": "813c7acaca966b5c632ff41eae66c0ac5fb28c2ffb22ed3742abb5ba0e1317e4",
  "model": "GALACTIC-BEACON-v14",
  "firmwareVersion": "14.0.0-galactic",
  "location": "PROXIMA-CENTAURI-B",
  "ts": "2026-05-08T18:40:00.514Z",
  "initialTelemetry": {
    "latency": 1810,
    "signalStrength": "0.2565",
    "galactic_sync": true
  },
  "source": "api",
  "updatedAt": "2026-05-08T18:40:00.515Z",
  "queuedAt": "2026-05-08T18:40:00.514Z"
}