{
  "deviceId": "1778265495234-b9201da9",
  "status": "queued",
  "createdAt": "2026-05-08T18:38:15.234Z",
  "hardwareIdHash": "06654ca2316da21f8d9692ec71a34d59bb721e9eee9ca8aedcb4568f87b79ece",
  "model": "GALACTIC-BEACON-v14",
  "firmwareVersion": "14.0.0-galactic",
  "location": "PROXIMA-CENTAURI-B",
  "ts": "2026-05-08T18:38:15.234Z",
  "initialTelemetry": {
    "latency": 2530,
    "signalStrength": "0.3526",
    "galactic_sync": true
  },
  "source": "api",
  "updatedAt": "2026-05-08T18:38:15.235Z",
  "queuedAt": "2026-05-08T18:38:15.235Z"
}