{
  "deviceId": "1778265510780-60803522",
  "status": "queued",
  "createdAt": "2026-05-08T18:38:30.780Z",
  "hardwareIdHash": "9395820fcf12a0d62c70ea8a717e9466b857c1c9dd64c32d2789890287a7240f",
  "model": "GALACTIC-BEACON-v14",
  "firmwareVersion": "14.0.0-galactic",
  "location": "PROXIMA-CENTAURI-B",
  "ts": "2026-05-08T18:38:30.780Z",
  "initialTelemetry": {
    "latency": 1727,
    "signalStrength": "0.2839",
    "galactic_sync": true
  },
  "source": "api",
  "updatedAt": "2026-05-08T18:38:30.780Z",
  "queuedAt": "2026-05-08T18:38:30.780Z"
}