{
  "deviceId": "1778265544979-de937579",
  "status": "queued",
  "createdAt": "2026-05-08T18:39:04.979Z",
  "hardwareIdHash": "2dec6234188a103b843d5c63ec768a5e091fdec29bc06b9b30c01e41adf25ab3",
  "model": "GALACTIC-BEACON-v14",
  "firmwareVersion": "14.0.0-galactic",
  "location": "PROXIMA-CENTAURI-B",
  "ts": "2026-05-08T18:39:04.979Z",
  "initialTelemetry": {
    "latency": 3767,
    "signalStrength": "0.2006",
    "galactic_sync": true
  },
  "source": "api",
  "updatedAt": "2026-05-08T18:39:04.980Z",
  "queuedAt": "2026-05-08T18:39:04.980Z"
}