{
  "deviceId": "1778265542657-6d6309b0",
  "status": "queued",
  "createdAt": "2026-05-08T18:39:02.657Z",
  "hardwareIdHash": "82f7236c3b548419dabcb90cc15aaf079d59fce920ae8a30f9d65633bd56c738",
  "model": "GALACTIC-BEACON-v14",
  "firmwareVersion": "14.0.0-galactic",
  "location": "PROXIMA-CENTAURI-B",
  "ts": "2026-05-08T18:39:02.657Z",
  "initialTelemetry": {
    "latency": 130,
    "signalStrength": "0.2792",
    "galactic_sync": true
  },
  "source": "api",
  "updatedAt": "2026-05-08T18:39:02.658Z",
  "queuedAt": "2026-05-08T18:39:02.658Z"
}