{
  "deviceId": "1778265586166-ad0daca2",
  "status": "queued",
  "createdAt": "2026-05-08T18:39:46.166Z",
  "hardwareIdHash": "b97c0681d6104440e0149f9d7a0b793fe889b678de4378c66241cb6f3a393f42",
  "model": "GALACTIC-BEACON-v14",
  "firmwareVersion": "14.0.0-galactic",
  "location": "PROXIMA-CENTAURI-B",
  "ts": "2026-05-08T18:39:46.166Z",
  "initialTelemetry": {
    "latency": 2667,
    "signalStrength": "0.8497",
    "galactic_sync": true
  },
  "source": "api",
  "updatedAt": "2026-05-08T18:39:46.167Z",
  "queuedAt": "2026-05-08T18:39:46.167Z"
}