{
  "deviceId": "1778265469021-652b9394",
  "status": "queued",
  "createdAt": "2026-05-08T18:37:49.021Z",
  "hardwareIdHash": "bcee46f20bfadca4b8fc3378c9066c3e3ad83ae29e712a2cbc0ba31d90efd79b",
  "model": "GALACTIC-BEACON-v14",
  "firmwareVersion": "14.0.0-galactic",
  "location": "PROXIMA-CENTAURI-B",
  "ts": "2026-05-08T18:37:49.021Z",
  "initialTelemetry": {
    "latency": 2623,
    "signalStrength": "0.9353",
    "galactic_sync": true
  },
  "source": "api",
  "updatedAt": "2026-05-08T18:37:49.022Z",
  "queuedAt": "2026-05-08T18:37:49.022Z"
}