{
  "deviceId": "1778265512059-b624a784",
  "status": "queued",
  "createdAt": "2026-05-08T18:38:32.059Z",
  "hardwareIdHash": "637b2c1212dc60473314ed9df9774abac66cef6dc671209aa00d07f4d89544c6",
  "model": "GALACTIC-BEACON-v14",
  "firmwareVersion": "14.0.0-galactic",
  "location": "PROXIMA-CENTAURI-B",
  "ts": "2026-05-08T18:38:32.059Z",
  "initialTelemetry": {
    "latency": 3769,
    "signalStrength": "0.2771",
    "galactic_sync": true
  },
  "source": "api",
  "updatedAt": "2026-05-08T18:38:32.061Z",
  "queuedAt": "2026-05-08T18:38:32.060Z"
}