{
  "deviceId": "1778265543376-eca299e0",
  "status": "queued",
  "createdAt": "2026-05-08T18:39:03.376Z",
  "hardwareIdHash": "67e29ceb2531b3652b7498483cbba7fef773916a05691e02737c195e3ea8b8c0",
  "model": "GALACTIC-BEACON-v14",
  "firmwareVersion": "14.0.0-galactic",
  "location": "PROXIMA-CENTAURI-B",
  "ts": "2026-05-08T18:39:03.376Z",
  "initialTelemetry": {
    "latency": 612,
    "signalStrength": "0.9509",
    "galactic_sync": true
  },
  "source": "api",
  "updatedAt": "2026-05-08T18:39:03.377Z",
  "queuedAt": "2026-05-08T18:39:03.376Z"
}