{
  "deviceId": "1778265626619-225e3e96",
  "status": "queued",
  "createdAt": "2026-05-08T18:40:26.619Z",
  "hardwareIdHash": "ba439f08a91fb09bf3c1685e222e6ec7d2271bf57c81e18febc9dca80344d71e",
  "model": "GALACTIC-BEACON-v14",
  "firmwareVersion": "14.0.0-galactic",
  "location": "PROXIMA-CENTAURI-B",
  "ts": "2026-05-08T18:40:26.619Z",
  "initialTelemetry": {
    "latency": 952,
    "signalStrength": "0.9012",
    "galactic_sync": true
  },
  "source": "api",
  "updatedAt": "2026-05-08T18:40:26.620Z",
  "queuedAt": "2026-05-08T18:40:26.620Z"
}