{
  "deviceId": "1778265593767-3e15fb77",
  "status": "queued",
  "createdAt": "2026-05-08T18:39:53.767Z",
  "hardwareIdHash": "ec0b5f99fd376f5424cd848c9c9f87260fce3e8393b7e768f7c5cb3830fa7aba",
  "model": "GALACTIC-BEACON-v14",
  "firmwareVersion": "14.0.0-galactic",
  "location": "PROXIMA-CENTAURI-B",
  "ts": "2026-05-08T18:39:53.767Z",
  "initialTelemetry": {
    "latency": 1210,
    "signalStrength": "0.3659",
    "galactic_sync": true
  },
  "source": "api",
  "updatedAt": "2026-05-08T18:39:53.768Z",
  "queuedAt": "2026-05-08T18:39:53.768Z"
}