{
  "deviceId": "1778185922552-a1c8903c",
  "status": "queued",
  "createdAt": "2026-05-07T20:32:02.552Z",
  "hardwareIdHash": "1318546769ab2e3c8da1b1a54279f513412f7684ce4a5ba3550ffc9bef7ea61e",
  "model": "NB-LOAD-TESTER-v1",
  "firmwareVersion": "1.0.0-stress",
  "location": "LUNAR-SURFACE-BETA",
  "ts": "2026-05-07T20:32:02.552Z",
  "initialTelemetry": {
    "battery": 96,
    "temp": 34,
    "heartbeat": true
  },
  "source": "api",
  "updatedAt": "2026-05-07T20:32:02.553Z",
  "queuedAt": "2026-05-07T20:32:02.553Z"
}