{
  "deviceId": "1778265629911-6d593f77",
  "status": "queued",
  "createdAt": "2026-05-08T18:40:29.911Z",
  "hardwareIdHash": "187e15aaf9b21ac811234e5f36da1fc07034990697bddaacac39b56ad0ae5712",
  "model": "GALACTIC-BEACON-v14",
  "firmwareVersion": "14.0.0-galactic",
  "location": "PROXIMA-CENTAURI-B",
  "ts": "2026-05-08T18:40:29.911Z",
  "initialTelemetry": {
    "latency": 2504,
    "signalStrength": "0.9408",
    "galactic_sync": true
  },
  "source": "api",
  "updatedAt": "2026-05-08T18:40:29.912Z",
  "queuedAt": "2026-05-08T18:40:29.912Z"
}