{
  "deviceId": "1778265566978-e5d69ccb",
  "status": "queued",
  "createdAt": "2026-05-08T18:39:26.978Z",
  "hardwareIdHash": "db22467ba585a6c4d9b3eec5285c580dca348004649bed124b7c5e09795a501b",
  "model": "GALACTIC-BEACON-v14",
  "firmwareVersion": "14.0.0-galactic",
  "location": "PROXIMA-CENTAURI-B",
  "ts": "2026-05-08T18:39:26.978Z",
  "initialTelemetry": {
    "latency": 363,
    "signalStrength": "0.7087",
    "galactic_sync": true
  },
  "source": "api",
  "updatedAt": "2026-05-08T18:39:26.979Z",
  "queuedAt": "2026-05-08T18:39:26.979Z"
}