{
  "deviceId": "1778265599082-0b19e1fe",
  "status": "queued",
  "createdAt": "2026-05-08T18:39:59.082Z",
  "hardwareIdHash": "15e889d574d96c7cae11fb0c941651ff475963c4972a23c9f0e342371e8f42a8",
  "model": "GALACTIC-BEACON-v14",
  "firmwareVersion": "14.0.0-galactic",
  "location": "PROXIMA-CENTAURI-B",
  "ts": "2026-05-08T18:39:59.082Z",
  "initialTelemetry": {
    "latency": 1688,
    "signalStrength": "0.0710",
    "galactic_sync": true
  },
  "source": "api",
  "updatedAt": "2026-05-08T18:39:59.084Z",
  "queuedAt": "2026-05-08T18:39:59.083Z"
}