{
  "deviceId": "1778265508816-ea2c3624",
  "status": "queued",
  "createdAt": "2026-05-08T18:38:28.816Z",
  "hardwareIdHash": "eacbc4a0ae3686f1ebfa24a59599a02ce4f412b738058f6692f66967d755cb5c",
  "model": "GALACTIC-BEACON-v14",
  "firmwareVersion": "14.0.0-galactic",
  "location": "PROXIMA-CENTAURI-B",
  "ts": "2026-05-08T18:38:28.816Z",
  "initialTelemetry": {
    "latency": 4623,
    "signalStrength": "0.1823",
    "galactic_sync": true
  },
  "source": "api",
  "updatedAt": "2026-05-08T18:38:28.817Z",
  "queuedAt": "2026-05-08T18:38:28.817Z"
}