{
  "deviceId": "1778265518509-91ad4497",
  "status": "queued",
  "createdAt": "2026-05-08T18:38:38.509Z",
  "hardwareIdHash": "b818ce138afbc57af45deaa50d9f53894f0e755e482c26d55640881eeb6f8d93",
  "model": "GALACTIC-BEACON-v14",
  "firmwareVersion": "14.0.0-galactic",
  "location": "PROXIMA-CENTAURI-B",
  "ts": "2026-05-08T18:38:38.509Z",
  "initialTelemetry": {
    "latency": 4406,
    "signalStrength": "0.1048",
    "galactic_sync": true
  },
  "source": "api",
  "updatedAt": "2026-05-08T18:38:38.511Z",
  "queuedAt": "2026-05-08T18:38:38.511Z"
}