{
  "deviceId": "1778185940757-c0ad3e39",
  "status": "queued",
  "createdAt": "2026-05-07T20:32:20.757Z",
  "hardwareIdHash": "df8024976de656eac44c11aa6f2427b3f6d95821c5ef954448cf7fb55c7edfd5",
  "model": "NB-LOAD-TESTER-v1",
  "firmwareVersion": "1.0.0-stress",
  "location": "LUNAR-SURFACE-BETA",
  "ts": "2026-05-07T20:32:20.757Z",
  "initialTelemetry": {
    "battery": 35,
    "temp": 0,
    "heartbeat": true
  },
  "source": "api",
  "updatedAt": "2026-05-07T20:32:20.758Z",
  "queuedAt": "2026-05-07T20:32:20.758Z"
}