{
  "deviceId": "1778265609030-8dcfb612",
  "status": "queued",
  "createdAt": "2026-05-08T18:40:09.030Z",
  "hardwareIdHash": "6aea145e6282a91e8a3793faebda33bc45214f21eae2340cd7dfafdb41b4a754",
  "model": "GALACTIC-BEACON-v14",
  "firmwareVersion": "14.0.0-galactic",
  "location": "PROXIMA-CENTAURI-B",
  "ts": "2026-05-08T18:40:09.030Z",
  "initialTelemetry": {
    "latency": 1216,
    "signalStrength": "0.9283",
    "galactic_sync": true
  },
  "source": "api",
  "updatedAt": "2026-05-08T18:40:09.032Z",
  "queuedAt": "2026-05-08T18:40:09.031Z"
}