{
  "deviceId": "1778265580326-3553cb7d",
  "status": "queued",
  "createdAt": "2026-05-08T18:39:40.327Z",
  "hardwareIdHash": "da6eb1ab7ace40e3c5d4ed028068679ce487e17661d32bf8da2c118ed44db147",
  "model": "GALACTIC-BEACON-v14",
  "firmwareVersion": "14.0.0-galactic",
  "location": "PROXIMA-CENTAURI-B",
  "ts": "2026-05-08T18:39:40.326Z",
  "initialTelemetry": {
    "latency": 1917,
    "signalStrength": "0.1368",
    "galactic_sync": true
  },
  "source": "api",
  "updatedAt": "2026-05-08T18:39:40.328Z",
  "queuedAt": "2026-05-08T18:39:40.327Z"
}