{
  "deviceId": "1778265465614-15601999",
  "status": "queued",
  "createdAt": "2026-05-08T18:37:45.614Z",
  "hardwareIdHash": "31a072357980206b4d875df0b6164cfc56c3376d5ccd24b0fb88b1f0246f66c8",
  "model": "GALACTIC-BEACON-v14",
  "firmwareVersion": "14.0.0-galactic",
  "location": "PROXIMA-CENTAURI-B",
  "ts": "2026-05-08T18:37:45.614Z",
  "initialTelemetry": {
    "latency": 4982,
    "signalStrength": "0.8449",
    "galactic_sync": true
  },
  "source": "api",
  "updatedAt": "2026-05-08T18:37:45.615Z",
  "queuedAt": "2026-05-08T18:37:45.615Z"
}