{
  "deviceId": "1778265467875-faf807ca",
  "status": "queued",
  "createdAt": "2026-05-08T18:37:47.875Z",
  "hardwareIdHash": "84df98791e47e2898aed8f604ade99167c08d3c638b5da5b46f8e2a7abbde76a",
  "model": "GALACTIC-BEACON-v14",
  "firmwareVersion": "14.0.0-galactic",
  "location": "PROXIMA-CENTAURI-B",
  "ts": "2026-05-08T18:37:47.875Z",
  "initialTelemetry": {
    "latency": 1453,
    "signalStrength": "0.2910",
    "galactic_sync": true
  },
  "source": "api",
  "updatedAt": "2026-05-08T18:37:47.876Z",
  "queuedAt": "2026-05-08T18:37:47.876Z"
}