{
  "deviceId": "1778265452889-366b0d9c",
  "status": "queued",
  "createdAt": "2026-05-08T18:37:32.890Z",
  "hardwareIdHash": "cc2275f0f0d5e46eebda9ec85903ecb1ae78f891fe1fb985198a017e4172e84c",
  "model": "GALACTIC-BEACON-v14",
  "firmwareVersion": "14.0.0-galactic",
  "location": "PROXIMA-CENTAURI-B",
  "ts": "2026-05-08T18:37:32.889Z",
  "initialTelemetry": {
    "latency": 4096,
    "signalStrength": "0.3896",
    "galactic_sync": true
  },
  "source": "api",
  "updatedAt": "2026-05-08T18:37:32.891Z",
  "queuedAt": "2026-05-08T18:37:32.890Z"
}