{
  "deviceId": "1778265490271-3b456d64",
  "status": "queued",
  "createdAt": "2026-05-08T18:38:10.272Z",
  "hardwareIdHash": "f1d6269b3c92c4dc46ecfa1514bef6f6be7381985d9644c7308abe864b298af1",
  "model": "GALACTIC-BEACON-v14",
  "firmwareVersion": "14.0.0-galactic",
  "location": "PROXIMA-CENTAURI-B",
  "ts": "2026-05-08T18:38:10.271Z",
  "initialTelemetry": {
    "latency": 340,
    "signalStrength": "0.6574",
    "galactic_sync": true
  },
  "source": "api",
  "updatedAt": "2026-05-08T18:38:10.273Z",
  "queuedAt": "2026-05-08T18:38:10.273Z"
}