{
  "deviceId": "1778265525649-367ad9d3",
  "status": "queued",
  "createdAt": "2026-05-08T18:38:45.649Z",
  "hardwareIdHash": "610ad6f39efc2f3f66d36fa7faf288117902e3a00bd1992139d9f38f2735b132",
  "model": "GALACTIC-BEACON-v14",
  "firmwareVersion": "14.0.0-galactic",
  "location": "PROXIMA-CENTAURI-B",
  "ts": "2026-05-08T18:38:45.649Z",
  "initialTelemetry": {
    "latency": 173,
    "signalStrength": "0.8350",
    "galactic_sync": true
  },
  "source": "api",
  "updatedAt": "2026-05-08T18:38:45.650Z",
  "queuedAt": "2026-05-08T18:38:45.649Z"
}