{
  "deviceId": "1778185924699-4eec0e7f",
  "status": "queued",
  "createdAt": "2026-05-07T20:32:04.699Z",
  "hardwareIdHash": "4423462d53cc6bc56c23049a71037b6101703b1d0e69fde01edad7158e139164",
  "model": "NB-LOAD-TESTER-v1",
  "firmwareVersion": "1.0.0-stress",
  "location": "LUNAR-SURFACE-BETA",
  "ts": "2026-05-07T20:32:04.699Z",
  "initialTelemetry": {
    "battery": 44,
    "temp": 15,
    "heartbeat": true
  },
  "source": "api",
  "updatedAt": "2026-05-07T20:32:04.700Z",
  "queuedAt": "2026-05-07T20:32:04.700Z"
}