{
  "deviceId": "1778265565888-321cc5ec",
  "status": "queued",
  "createdAt": "2026-05-08T18:39:25.888Z",
  "hardwareIdHash": "e4857ab995e647368e472fef9158d50e8fe5e75e28d62a7167f564085bb3ed47",
  "model": "GALACTIC-BEACON-v14",
  "firmwareVersion": "14.0.0-galactic",
  "location": "PROXIMA-CENTAURI-B",
  "ts": "2026-05-08T18:39:25.888Z",
  "initialTelemetry": {
    "latency": 4233,
    "signalStrength": "0.0039",
    "galactic_sync": true
  },
  "source": "api",
  "updatedAt": "2026-05-08T18:39:25.889Z",
  "queuedAt": "2026-05-08T18:39:25.889Z"
}