{
  "deviceId": "1778265492392-196642da",
  "status": "queued",
  "createdAt": "2026-05-08T18:38:12.392Z",
  "hardwareIdHash": "a22bce6a5a3e4fb8cb59dc3665ce70165bd69138cfd92256a106447da2085346",
  "model": "GALACTIC-BEACON-v14",
  "firmwareVersion": "14.0.0-galactic",
  "location": "PROXIMA-CENTAURI-B",
  "ts": "2026-05-08T18:38:12.392Z",
  "initialTelemetry": {
    "latency": 2434,
    "signalStrength": "0.0075",
    "galactic_sync": true
  },
  "source": "api",
  "updatedAt": "2026-05-08T18:38:12.393Z",
  "queuedAt": "2026-05-08T18:38:12.393Z"
}