{
  "deviceId": "1778265479135-272feca6",
  "status": "queued",
  "createdAt": "2026-05-08T18:37:59.136Z",
  "hardwareIdHash": "cd755088acd3b89cbb2c290238ada1117027a9d8d19b261d7c4a25953d0c9165",
  "model": "GALACTIC-BEACON-v14",
  "firmwareVersion": "14.0.0-galactic",
  "location": "PROXIMA-CENTAURI-B",
  "ts": "2026-05-08T18:37:59.135Z",
  "initialTelemetry": {
    "latency": 2624,
    "signalStrength": "0.7142",
    "galactic_sync": true
  },
  "source": "api",
  "updatedAt": "2026-05-08T18:37:59.136Z",
  "queuedAt": "2026-05-08T18:37:59.136Z"
}