{
  "deviceId": "1778265632369-fbf00163",
  "status": "queued",
  "createdAt": "2026-05-08T18:40:32.369Z",
  "hardwareIdHash": "3dadbf5eb393378bf1c542341739864db2944fbda145eb7af2124688e0618cb3",
  "model": "GALACTIC-BEACON-v14",
  "firmwareVersion": "14.0.0-galactic",
  "location": "PROXIMA-CENTAURI-B",
  "ts": "2026-05-08T18:40:32.369Z",
  "initialTelemetry": {
    "latency": 872,
    "signalStrength": "0.4101",
    "galactic_sync": true
  },
  "source": "api",
  "updatedAt": "2026-05-08T18:40:32.370Z",
  "queuedAt": "2026-05-08T18:40:32.370Z"
}