{
  "deviceId": "1778265494680-cfef3967",
  "status": "queued",
  "createdAt": "2026-05-08T18:38:14.680Z",
  "hardwareIdHash": "2f3b513bbf8ec93e95c75e1c2241e8d8a70a281f8050f2516bfb40e26dcb0199",
  "model": "GALACTIC-BEACON-v14",
  "firmwareVersion": "14.0.0-galactic",
  "location": "PROXIMA-CENTAURI-B",
  "ts": "2026-05-08T18:38:14.680Z",
  "initialTelemetry": {
    "latency": 2243,
    "signalStrength": "0.6798",
    "galactic_sync": true
  },
  "source": "api",
  "updatedAt": "2026-05-08T18:38:14.681Z",
  "queuedAt": "2026-05-08T18:38:14.681Z"
}