{
  "deviceId": "1778265590999-3860fa95",
  "status": "queued",
  "createdAt": "2026-05-08T18:39:50.999Z",
  "hardwareIdHash": "fc778b8176e7fe9be45e25cdc80eadfbcccc2d6392d66b458bbfc7625ce92338",
  "model": "GALACTIC-BEACON-v14",
  "firmwareVersion": "14.0.0-galactic",
  "location": "PROXIMA-CENTAURI-B",
  "ts": "2026-05-08T18:39:50.999Z",
  "initialTelemetry": {
    "latency": 4667,
    "signalStrength": "0.1125",
    "galactic_sync": true
  },
  "source": "api",
  "updatedAt": "2026-05-08T18:39:51.000Z",
  "queuedAt": "2026-05-08T18:39:51.000Z"
}