{
  "deviceId": "1778265566904-00f6a169",
  "status": "queued",
  "createdAt": "2026-05-08T18:39:26.905Z",
  "hardwareIdHash": "e58d593bbfd8032e198b1dbf25efc6cd81ea2d207585b2dac6405293d7a13d5c",
  "model": "GALACTIC-BEACON-v14",
  "firmwareVersion": "14.0.0-galactic",
  "location": "PROXIMA-CENTAURI-B",
  "ts": "2026-05-08T18:39:26.904Z",
  "initialTelemetry": {
    "latency": 208,
    "signalStrength": "0.4328",
    "galactic_sync": true
  },
  "source": "api",
  "updatedAt": "2026-05-08T18:39:26.909Z",
  "queuedAt": "2026-05-08T18:39:26.909Z"
}