{
  "deviceId": "1778265544614-4b8d7138",
  "status": "queued",
  "createdAt": "2026-05-08T18:39:04.614Z",
  "hardwareIdHash": "f03c34675ac42a3cb9c4aa6f1450945e281d3b407d7735a4d55ba8dafd5db44c",
  "model": "GALACTIC-BEACON-v14",
  "firmwareVersion": "14.0.0-galactic",
  "location": "PROXIMA-CENTAURI-B",
  "ts": "2026-05-08T18:39:04.614Z",
  "initialTelemetry": {
    "latency": 361,
    "signalStrength": "0.8953",
    "galactic_sync": true
  },
  "source": "api",
  "updatedAt": "2026-05-08T18:39:04.615Z",
  "queuedAt": "2026-05-08T18:39:04.615Z"
}