{
  "deviceId": "1778265474437-6c22dd35",
  "status": "queued",
  "createdAt": "2026-05-08T18:37:54.437Z",
  "hardwareIdHash": "422acd424891650a2dc29928c52baf77b51c9abbfa99a7d2f125ae79f7f63725",
  "model": "GALACTIC-BEACON-v14",
  "firmwareVersion": "14.0.0-galactic",
  "location": "PROXIMA-CENTAURI-B",
  "ts": "2026-05-08T18:37:54.437Z",
  "initialTelemetry": {
    "latency": 1472,
    "signalStrength": "0.9180",
    "galactic_sync": true
  },
  "source": "api",
  "updatedAt": "2026-05-08T18:37:54.438Z",
  "queuedAt": "2026-05-08T18:37:54.438Z"
}