{
  "deviceId": "1778265629836-5fafd1e7",
  "status": "queued",
  "createdAt": "2026-05-08T18:40:29.836Z",
  "hardwareIdHash": "419b1cb278b316e9947179842fdb3017f2b7523724b616b91eb4ed20c62360d2",
  "model": "GALACTIC-BEACON-v14",
  "firmwareVersion": "14.0.0-galactic",
  "location": "PROXIMA-CENTAURI-B",
  "ts": "2026-05-08T18:40:29.836Z",
  "initialTelemetry": {
    "latency": 917,
    "signalStrength": "0.9891",
    "galactic_sync": true
  },
  "source": "api",
  "updatedAt": "2026-05-08T18:40:29.837Z",
  "queuedAt": "2026-05-08T18:40:29.837Z"
}