{
  "deviceId": "1778265502422-ac65a9ae",
  "status": "queued",
  "createdAt": "2026-05-08T18:38:22.422Z",
  "hardwareIdHash": "c2f90800529a15d99f12294ce428dee01bfaf8c2ab84a997e9b454de4ad8799f",
  "model": "GALACTIC-BEACON-v14",
  "firmwareVersion": "14.0.0-galactic",
  "location": "PROXIMA-CENTAURI-B",
  "ts": "2026-05-08T18:38:22.422Z",
  "initialTelemetry": {
    "latency": 4238,
    "signalStrength": "0.4153",
    "galactic_sync": true
  },
  "source": "api",
  "updatedAt": "2026-05-08T18:38:22.422Z",
  "queuedAt": "2026-05-08T18:38:22.422Z"
}