{
  "deviceId": "1778265588914-729e7099",
  "status": "queued",
  "createdAt": "2026-05-08T18:39:48.914Z",
  "hardwareIdHash": "5bbfc73c57445dd2dc09d4f10c3a6dfa3d292c204f4370344cd09090f4867251",
  "model": "GALACTIC-BEACON-v14",
  "firmwareVersion": "14.0.0-galactic",
  "location": "PROXIMA-CENTAURI-B",
  "ts": "2026-05-08T18:39:48.914Z",
  "initialTelemetry": {
    "latency": 414,
    "signalStrength": "0.3070",
    "galactic_sync": true
  },
  "source": "api",
  "updatedAt": "2026-05-08T18:39:48.915Z",
  "queuedAt": "2026-05-08T18:39:48.915Z"
}