{
  "deviceId": "1778265596005-18d042fe",
  "status": "queued",
  "createdAt": "2026-05-08T18:39:56.005Z",
  "hardwareIdHash": "8a5ba92b49aa8cacb2d748da53ac8bca4e0811237845f35b6a5f9718265186ac",
  "model": "GALACTIC-BEACON-v14",
  "firmwareVersion": "14.0.0-galactic",
  "location": "PROXIMA-CENTAURI-B",
  "ts": "2026-05-08T18:39:56.005Z",
  "initialTelemetry": {
    "latency": 761,
    "signalStrength": "0.5131",
    "galactic_sync": true
  },
  "source": "api",
  "updatedAt": "2026-05-08T18:39:56.006Z",
  "queuedAt": "2026-05-08T18:39:56.006Z"
}