{
  "deviceId": "1778265507143-2470f588",
  "status": "queued",
  "createdAt": "2026-05-08T18:38:27.143Z",
  "hardwareIdHash": "96611691b7600bf0d02b58b8ee44b3d1bdecc19758410c9fcaeed6a9cf6dc8da",
  "model": "GALACTIC-BEACON-v14",
  "firmwareVersion": "14.0.0-galactic",
  "location": "PROXIMA-CENTAURI-B",
  "ts": "2026-05-08T18:38:27.143Z",
  "initialTelemetry": {
    "latency": 3596,
    "signalStrength": "0.7867",
    "galactic_sync": true
  },
  "source": "api",
  "updatedAt": "2026-05-08T18:38:27.144Z",
  "queuedAt": "2026-05-08T18:38:27.144Z"
}