{
  "deviceId": "1778185940917-59a8e097",
  "status": "queued",
  "createdAt": "2026-05-07T20:32:20.917Z",
  "hardwareIdHash": "09b9ee2a45a59b2a30f150076f2d715c3800f472aca1298269c270e6a91c36fc",
  "model": "NB-LOAD-TESTER-v1",
  "firmwareVersion": "1.0.0-stress",
  "location": "LUNAR-SURFACE-BETA",
  "ts": "2026-05-07T20:32:20.917Z",
  "initialTelemetry": {
    "battery": 71,
    "temp": 11,
    "heartbeat": true
  },
  "source": "api",
  "updatedAt": "2026-05-07T20:32:20.918Z",
  "queuedAt": "2026-05-07T20:32:20.918Z"
}