{
  "deviceId": "1778265464785-fd0b23ee",
  "status": "queued",
  "createdAt": "2026-05-08T18:37:44.785Z",
  "hardwareIdHash": "91542746b5391a896756248645cbb3120e0b76e71f3547a7cb45ac8c8453ec53",
  "model": "GALACTIC-BEACON-v14",
  "firmwareVersion": "14.0.0-galactic",
  "location": "PROXIMA-CENTAURI-B",
  "ts": "2026-05-08T18:37:44.785Z",
  "initialTelemetry": {
    "latency": 1865,
    "signalStrength": "0.2444",
    "galactic_sync": true
  },
  "source": "api",
  "updatedAt": "2026-05-08T18:37:44.786Z",
  "queuedAt": "2026-05-08T18:37:44.786Z"
}