{
  "deviceId": "1778265479596-c447890a",
  "status": "queued",
  "createdAt": "2026-05-08T18:37:59.596Z",
  "hardwareIdHash": "5e269d6cc3ab14e95d3371c38c2b0e560af78a8a0253d7deea14df96dd87f1ba",
  "model": "GALACTIC-BEACON-v14",
  "firmwareVersion": "14.0.0-galactic",
  "location": "PROXIMA-CENTAURI-B",
  "ts": "2026-05-08T18:37:59.596Z",
  "initialTelemetry": {
    "latency": 2244,
    "signalStrength": "0.1346",
    "galactic_sync": true
  },
  "source": "api",
  "updatedAt": "2026-05-08T18:37:59.598Z",
  "queuedAt": "2026-05-08T18:37:59.597Z"
}