{
  "deviceId": "1778185924964-5d22c068",
  "status": "queued",
  "createdAt": "2026-05-07T20:32:04.964Z",
  "hardwareIdHash": "4755b16f331eb549e6eadf076556574346b409e09e84d876e5ea0cf67023c084",
  "model": "NB-LOAD-TESTER-v1",
  "firmwareVersion": "1.0.0-stress",
  "location": "LUNAR-SURFACE-BETA",
  "ts": "2026-05-07T20:32:04.964Z",
  "initialTelemetry": {
    "battery": 45,
    "temp": 14,
    "heartbeat": true
  },
  "source": "api",
  "updatedAt": "2026-05-07T20:32:04.965Z",
  "queuedAt": "2026-05-07T20:32:04.964Z"
}