{
  "deviceId": "1778265568552-1f54d96a",
  "status": "queued",
  "createdAt": "2026-05-08T18:39:28.552Z",
  "hardwareIdHash": "bbc07501799f20e3409ea7ea87b5137f55510222c706b43f3c59eb6b9e873ab5",
  "model": "GALACTIC-BEACON-v14",
  "firmwareVersion": "14.0.0-galactic",
  "location": "PROXIMA-CENTAURI-B",
  "ts": "2026-05-08T18:39:28.552Z",
  "initialTelemetry": {
    "latency": 2368,
    "signalStrength": "0.4446",
    "galactic_sync": true
  },
  "source": "api",
  "updatedAt": "2026-05-08T18:39:28.552Z",
  "queuedAt": "2026-05-08T18:39:28.552Z"
}