{
  "deviceId": "1778265533110-4aba8e81",
  "status": "queued",
  "createdAt": "2026-05-08T18:38:53.110Z",
  "hardwareIdHash": "fc572b35bdee47344283eb33044f788dcb58fbc1ac2a274aaa4dd56b7adf17c4",
  "model": "GALACTIC-BEACON-v14",
  "firmwareVersion": "14.0.0-galactic",
  "location": "PROXIMA-CENTAURI-B",
  "ts": "2026-05-08T18:38:53.110Z",
  "initialTelemetry": {
    "latency": 1823,
    "signalStrength": "0.8175",
    "galactic_sync": true
  },
  "source": "api",
  "updatedAt": "2026-05-08T18:38:53.113Z",
  "queuedAt": "2026-05-08T18:38:53.113Z"
}