{
  "deviceId": "1778265506875-837dc66b",
  "status": "queued",
  "createdAt": "2026-05-08T18:38:26.875Z",
  "hardwareIdHash": "d9dca43e1e7b1c243d72ec95646c277c416a127d362f4bdccc4b4fce52532f38",
  "model": "GALACTIC-BEACON-v14",
  "firmwareVersion": "14.0.0-galactic",
  "location": "PROXIMA-CENTAURI-B",
  "ts": "2026-05-08T18:38:26.875Z",
  "initialTelemetry": {
    "latency": 3360,
    "signalStrength": "0.2893",
    "galactic_sync": true
  },
  "source": "api",
  "updatedAt": "2026-05-08T18:38:26.876Z",
  "queuedAt": "2026-05-08T18:38:26.876Z"
}