{
  "deviceId": "1778265524327-f1c1160e",
  "status": "queued",
  "createdAt": "2026-05-08T18:38:44.327Z",
  "hardwareIdHash": "0d55c5e4492b18d1a2727d70739b7aecfd02cc895d3d69d186c03b6d97294c52",
  "model": "GALACTIC-BEACON-v14",
  "firmwareVersion": "14.0.0-galactic",
  "location": "PROXIMA-CENTAURI-B",
  "ts": "2026-05-08T18:38:44.327Z",
  "initialTelemetry": {
    "latency": 2850,
    "signalStrength": "0.6711",
    "galactic_sync": true
  },
  "source": "api",
  "updatedAt": "2026-05-08T18:38:44.328Z",
  "queuedAt": "2026-05-08T18:38:44.328Z"
}