{
  "deviceId": "1778265529100-78cb3180",
  "status": "queued",
  "createdAt": "2026-05-08T18:38:49.100Z",
  "hardwareIdHash": "6ef9958903ae9bc1313a2c5c4ed44dfd224853b6c429da929bded1b7a492b487",
  "model": "GALACTIC-BEACON-v14",
  "firmwareVersion": "14.0.0-galactic",
  "location": "PROXIMA-CENTAURI-B",
  "ts": "2026-05-08T18:38:49.100Z",
  "initialTelemetry": {
    "latency": 2079,
    "signalStrength": "0.8836",
    "galactic_sync": true
  },
  "source": "api",
  "updatedAt": "2026-05-08T18:38:49.101Z",
  "queuedAt": "2026-05-08T18:38:49.101Z"
}