{
  "deviceId": "1778265460442-9e894d3a",
  "status": "queued",
  "createdAt": "2026-05-08T18:37:40.442Z",
  "hardwareIdHash": "46dfcc7e3681ea787eb1cf1d530632a55a28b32dc7e3116ea94b747a234d720f",
  "model": "GALACTIC-BEACON-v14",
  "firmwareVersion": "14.0.0-galactic",
  "location": "PROXIMA-CENTAURI-B",
  "ts": "2026-05-08T18:37:40.442Z",
  "initialTelemetry": {
    "latency": 92,
    "signalStrength": "0.2391",
    "galactic_sync": true
  },
  "source": "api",
  "updatedAt": "2026-05-08T18:37:40.444Z",
  "queuedAt": "2026-05-08T18:37:40.444Z"
}