{
  "deviceId": "1778265537218-a6086ab3",
  "status": "queued",
  "createdAt": "2026-05-08T18:38:57.218Z",
  "hardwareIdHash": "53679b60d7aad5b4969e66cb8cca87c3083f1cbaada7b6dc6a82d072dc96b169",
  "model": "GALACTIC-BEACON-v14",
  "firmwareVersion": "14.0.0-galactic",
  "location": "PROXIMA-CENTAURI-B",
  "ts": "2026-05-08T18:38:57.218Z",
  "initialTelemetry": {
    "latency": 522,
    "signalStrength": "0.5435",
    "galactic_sync": true
  },
  "source": "api",
  "updatedAt": "2026-05-08T18:38:57.219Z",
  "queuedAt": "2026-05-08T18:38:57.219Z"
}