{
  "deviceId": "1778265610793-f7c9ce42",
  "status": "queued",
  "createdAt": "2026-05-08T18:40:10.793Z",
  "hardwareIdHash": "e62670ad9149da7359e4fd688b69666850bb40657fceb399b86ceb8312209f93",
  "model": "GALACTIC-BEACON-v14",
  "firmwareVersion": "14.0.0-galactic",
  "location": "PROXIMA-CENTAURI-B",
  "ts": "2026-05-08T18:40:10.793Z",
  "initialTelemetry": {
    "latency": 471,
    "signalStrength": "0.7996",
    "galactic_sync": true
  },
  "source": "api",
  "updatedAt": "2026-05-08T18:40:10.795Z",
  "queuedAt": "2026-05-08T18:40:10.795Z"
}