{
  "deviceId": "1778265582260-9a7a65e1",
  "status": "queued",
  "createdAt": "2026-05-08T18:39:42.260Z",
  "hardwareIdHash": "93d378ba40f2cabb8a29f50b040459eef8da4b5bd2043a2f9a7180034e6038f8",
  "model": "GALACTIC-BEACON-v14",
  "firmwareVersion": "14.0.0-galactic",
  "location": "PROXIMA-CENTAURI-B",
  "ts": "2026-05-08T18:39:42.260Z",
  "initialTelemetry": {
    "latency": 158,
    "signalStrength": "0.7930",
    "galactic_sync": true
  },
  "source": "api",
  "updatedAt": "2026-05-08T18:39:42.261Z",
  "queuedAt": "2026-05-08T18:39:42.261Z"
}