{
  "deviceId": "1778265455920-39e4b23e",
  "status": "queued",
  "createdAt": "2026-05-08T18:37:35.920Z",
  "hardwareIdHash": "dad744aa31d496317efc3d93959d8672f4a7b2e14aebf89ef2da4f28004bc7ff",
  "model": "GALACTIC-BEACON-v14",
  "firmwareVersion": "14.0.0-galactic",
  "location": "PROXIMA-CENTAURI-B",
  "ts": "2026-05-08T18:37:35.920Z",
  "initialTelemetry": {
    "latency": 1916,
    "signalStrength": "0.4124",
    "galactic_sync": true
  },
  "source": "api",
  "updatedAt": "2026-05-08T18:37:35.921Z",
  "queuedAt": "2026-05-08T18:37:35.920Z"
}