{
  "deviceId": "1778265574424-478007cb",
  "status": "queued",
  "createdAt": "2026-05-08T18:39:34.424Z",
  "hardwareIdHash": "258f33ddd84525659ddbb5c327ca37b325db71667bd8fd5424eca52f9f72df24",
  "model": "GALACTIC-BEACON-v14",
  "firmwareVersion": "14.0.0-galactic",
  "location": "PROXIMA-CENTAURI-B",
  "ts": "2026-05-08T18:39:34.424Z",
  "initialTelemetry": {
    "latency": 2605,
    "signalStrength": "0.5315",
    "galactic_sync": true
  },
  "source": "api",
  "updatedAt": "2026-05-08T18:39:34.425Z",
  "queuedAt": "2026-05-08T18:39:34.425Z"
}