{
  "deviceId": "1778265636731-4619316f",
  "status": "queued",
  "createdAt": "2026-05-08T18:40:36.731Z",
  "hardwareIdHash": "eee0ec3ad3cc1639ad583da8d042154b9f5b27cfe1d13b8882dfea8198def917",
  "model": "GALACTIC-BEACON-v14",
  "firmwareVersion": "14.0.0-galactic",
  "location": "PROXIMA-CENTAURI-B",
  "ts": "2026-05-08T18:40:36.731Z",
  "initialTelemetry": {
    "latency": 3974,
    "signalStrength": "0.2028",
    "galactic_sync": true
  },
  "source": "api",
  "updatedAt": "2026-05-08T18:40:36.732Z",
  "queuedAt": "2026-05-08T18:40:36.732Z"
}