{
  "deviceId": "1778265607594-3ee6f3c3",
  "status": "queued",
  "createdAt": "2026-05-08T18:40:07.594Z",
  "hardwareIdHash": "3513d92af757ce5e284e158c1e28fcc3a0b06833207b211b9445f0196785f010",
  "model": "GALACTIC-BEACON-v14",
  "firmwareVersion": "14.0.0-galactic",
  "location": "PROXIMA-CENTAURI-B",
  "ts": "2026-05-08T18:40:07.594Z",
  "initialTelemetry": {
    "latency": 3072,
    "signalStrength": "0.3796",
    "galactic_sync": true
  },
  "source": "api",
  "updatedAt": "2026-05-08T18:40:07.595Z",
  "queuedAt": "2026-05-08T18:40:07.595Z"
}