{
  "deviceId": "1778265601671-d50616c4",
  "status": "queued",
  "createdAt": "2026-05-08T18:40:01.671Z",
  "hardwareIdHash": "e7a57467ba1a5a6b6c29fd851d9aba7684da0734a62a0d6e052fd31074a7a66b",
  "model": "GALACTIC-BEACON-v14",
  "firmwareVersion": "14.0.0-galactic",
  "location": "PROXIMA-CENTAURI-B",
  "ts": "2026-05-08T18:40:01.671Z",
  "initialTelemetry": {
    "latency": 750,
    "signalStrength": "0.5882",
    "galactic_sync": true
  },
  "source": "api",
  "updatedAt": "2026-05-08T18:40:01.671Z",
  "queuedAt": "2026-05-08T18:40:01.671Z"
}