{
  "deviceId": "1778265535884-c7fa8272",
  "status": "queued",
  "createdAt": "2026-05-08T18:38:55.884Z",
  "hardwareIdHash": "ade30f58fccc4386bf91e344f134775491081e9fd312bd948aa1b7a2dff3bb9f",
  "model": "GALACTIC-BEACON-v14",
  "firmwareVersion": "14.0.0-galactic",
  "location": "PROXIMA-CENTAURI-B",
  "ts": "2026-05-08T18:38:55.884Z",
  "initialTelemetry": {
    "latency": 2323,
    "signalStrength": "0.4951",
    "galactic_sync": true
  },
  "source": "api",
  "updatedAt": "2026-05-08T18:38:55.885Z",
  "queuedAt": "2026-05-08T18:38:55.885Z"
}