{
  "deviceId": "1778265634831-1b3d711c",
  "status": "queued",
  "createdAt": "2026-05-08T18:40:34.831Z",
  "hardwareIdHash": "9f4af06ba375ec9ef44f5e3cd5cba80de1af3d384b3380b3928e1007600ed2b9",
  "model": "GALACTIC-BEACON-v14",
  "firmwareVersion": "14.0.0-galactic",
  "location": "PROXIMA-CENTAURI-B",
  "ts": "2026-05-08T18:40:34.831Z",
  "initialTelemetry": {
    "latency": 691,
    "signalStrength": "0.1498",
    "galactic_sync": true
  },
  "source": "api",
  "updatedAt": "2026-05-08T18:40:34.832Z",
  "queuedAt": "2026-05-08T18:40:34.832Z"
}