{
  "deviceId": "1778265500307-fa67375a",
  "status": "queued",
  "createdAt": "2026-05-08T18:38:20.307Z",
  "hardwareIdHash": "938088c1ba4171821b5ff000a32f1dba1e46ae7965ffab4cf8a5093ec82c6f5b",
  "model": "GALACTIC-BEACON-v14",
  "firmwareVersion": "14.0.0-galactic",
  "location": "PROXIMA-CENTAURI-B",
  "ts": "2026-05-08T18:38:20.307Z",
  "initialTelemetry": {
    "latency": 4231,
    "signalStrength": "0.6527",
    "galactic_sync": true
  },
  "source": "api",
  "updatedAt": "2026-05-08T18:38:20.309Z",
  "queuedAt": "2026-05-08T18:38:20.308Z"
}