{
  "deviceId": "1778265617960-a0219a59",
  "status": "queued",
  "createdAt": "2026-05-08T18:40:17.960Z",
  "hardwareIdHash": "c1afb0692b954cb5daa0d57533157e8e96ba4dc3cab6ecca32c80c4ba58cdaa5",
  "model": "GALACTIC-BEACON-v14",
  "firmwareVersion": "14.0.0-galactic",
  "location": "PROXIMA-CENTAURI-B",
  "ts": "2026-05-08T18:40:17.960Z",
  "initialTelemetry": {
    "latency": 3511,
    "signalStrength": "0.2998",
    "galactic_sync": true
  },
  "source": "api",
  "updatedAt": "2026-05-08T18:40:17.961Z",
  "queuedAt": "2026-05-08T18:40:17.961Z"
}