{
  "deviceId": "1778265487333-5eafe399",
  "status": "queued",
  "createdAt": "2026-05-08T18:38:07.333Z",
  "hardwareIdHash": "0d2601197942fca0a4098f56fb7b64d644a01aa798c8dc53f07e990541a3f205",
  "model": "GALACTIC-BEACON-v14",
  "firmwareVersion": "14.0.0-galactic",
  "location": "PROXIMA-CENTAURI-B",
  "ts": "2026-05-08T18:38:07.333Z",
  "initialTelemetry": {
    "latency": 2547,
    "signalStrength": "0.5283",
    "galactic_sync": true
  },
  "source": "api",
  "updatedAt": "2026-05-08T18:38:07.335Z",
  "queuedAt": "2026-05-08T18:38:07.334Z"
}