{
  "deviceId": "1778265464140-078b2b92",
  "status": "queued",
  "createdAt": "2026-05-08T18:37:44.140Z",
  "hardwareIdHash": "200c951c39541d19c7a3725132be0254174ac81a9c9cc500439db3f18e95df2d",
  "model": "GALACTIC-BEACON-v14",
  "firmwareVersion": "14.0.0-galactic",
  "location": "PROXIMA-CENTAURI-B",
  "ts": "2026-05-08T18:37:44.140Z",
  "initialTelemetry": {
    "latency": 1317,
    "signalStrength": "0.1446",
    "galactic_sync": true
  },
  "source": "api",
  "updatedAt": "2026-05-08T18:37:44.141Z",
  "queuedAt": "2026-05-08T18:37:44.141Z"
}