{
  "deviceId": "1778185928110-7b61ca70",
  "status": "queued",
  "createdAt": "2026-05-07T20:32:08.110Z",
  "hardwareIdHash": "2392b59e8306fd6bd9cdb12bb2ef30b6c26e5bfb94b9ffdac551d82d183ee2dc",
  "model": "NB-LOAD-TESTER-v1",
  "firmwareVersion": "1.0.0-stress",
  "location": "LUNAR-SURFACE-BETA",
  "ts": "2026-05-07T20:32:08.110Z",
  "initialTelemetry": {
    "battery": 18,
    "temp": 21,
    "heartbeat": true
  },
  "source": "api",
  "updatedAt": "2026-05-07T20:32:08.111Z",
  "queuedAt": "2026-05-07T20:32:08.111Z"
}