{
  "deviceId": "1778265576401-d01c5707",
  "status": "queued",
  "createdAt": "2026-05-08T18:39:36.401Z",
  "hardwareIdHash": "f6c3a979f741c83df81e147c907a5e44c02c2416f0895b5ee7e00740aeb23617",
  "model": "GALACTIC-BEACON-v14",
  "firmwareVersion": "14.0.0-galactic",
  "location": "PROXIMA-CENTAURI-B",
  "ts": "2026-05-08T18:39:36.401Z",
  "initialTelemetry": {
    "latency": 1976,
    "signalStrength": "0.6818",
    "galactic_sync": true
  },
  "source": "api",
  "updatedAt": "2026-05-08T18:39:36.402Z",
  "queuedAt": "2026-05-08T18:39:36.402Z"
}