{
  "deviceId": "1778265564923-98bcb18d",
  "status": "queued",
  "createdAt": "2026-05-08T18:39:24.923Z",
  "hardwareIdHash": "34f11ab5a8d4c0eb5d2ea2211d38ee163da1e37da964364e017d4c60ed40ddcf",
  "model": "GALACTIC-BEACON-v14",
  "firmwareVersion": "14.0.0-galactic",
  "location": "PROXIMA-CENTAURI-B",
  "ts": "2026-05-08T18:39:24.923Z",
  "initialTelemetry": {
    "latency": 3292,
    "signalStrength": "0.8814",
    "galactic_sync": true
  },
  "source": "api",
  "updatedAt": "2026-05-08T18:39:24.924Z",
  "queuedAt": "2026-05-08T18:39:24.924Z"
}